ALU.v
`timescale 1ns / 1ps

module ALU (in1, in2, op, out, carryout, overflow, rst, clk);
    input [7:0] in1;
    input [7:0] in2;
    input [3:0] op;
    input rst;
    input clk;
    output reg [7:0] out;
    output reg carryout;
    output reg overflow;

    always @(posedge clk or posedge rst)
    begin
        if(rst==1)
        begin 
            out=0;
            carryout=0;
            overflow=0;
        end
        
        else
        begin
            overflow=0;
            carryout=0;
            case(op)
                4'b0000: {carryout,out} = in1+in2;
                4'b0001: {carryout,out} = in1-in2; 
                4'b0010: begin
                            out = in1*in2;
                            overflow = (in1*in2>255);
                         end
                         
                4'b0011: begin
                            if(in2==0)
                                begin
                                    out = 8'b11111111;
                                    overflow =1;
                                end
                            else
                                out = in1/in2;
                         end

                4'b0100: out = in1&in2;
                4'b0101: out = in1|in2;
                4'b0110: out = in1^in2;
                4'b0111: out = ~in1;
                4'b1000: out = out<<1;
                4'b1001: out = out>>1;
                4'b1010: out = {in1[6:0], in1[7]};
                4'b1011: out = {in1[0], in1[7:1]};
                4'b1100: out = (in1 > in2) ? 1 : 0; 
                4'b1101: out = (in1 == in2) ? 1 : 0;
                default: out = out;
            endcase

            //overflow detection for addition and substraction only 
            if(op==4'b0000 || op==4'b0001)
            begin
                overflow = (in1[7]==in2[7]) && (out[7]!=in1[7]);
            end
        end
    end

endmodule

tb_alu.v
`timescale 1ns / 1ps

module tb;

    reg [7:0] in1;
    reg [7:0] in2;
    reg [3:0] op;
    reg rst;
    reg clk;
    wire [7:0] out;
    wire carryout;
    wire overflow;
    
 

    ALU dut (.in1(in1),.in2(in2),.op(op),.out(out),.carryout(carryout),.overflow(overflow),.rst(rst),.clk(clk));
    
    initial begin
        rst = 1;   
        in1 = 0;
        in2 = 0;
        op = 0;
        $dumpfile("waveform.vcd");
        $dumpvars(0, tb);   

        #5 rst = 0; 
        in1 = 25; in2 = 18; 
        #10 op = 4'b0000; 
        #10 op = 4'b0001;  
        #10 op = 4'b0010;  
        #10 op = 4'b0011;  
        #10 op = 4'b0100;  
        #10 op = 4'b0101;  
        #10 op = 4'b0110;  
        #10 op = 4'b0111;  
        #10 op = 4'b1000;  
        #10 op = 4'b1001;  
        #10 op = 4'b1010;  
        #10 op = 4'b1011;  
        #10 op = 4'b1100;  
        #10 op = 4'b1101;  
        
        // End simulation
        #10 $finish;
    end
    
    // Clock generation
    initial begin
        clk = 0;
        forever #5 clk = ~clk;
    end

endmodule

waveform.vcd
$version Generated by VerilatedVcd $end
$timescale 1ps $end
 $scope module TOP $end
  $scope module tb $end
   $var wire 8 & in1 [7:0] $end
   $var wire 8 ' in2 [7:0] $end
   $var wire 4 ( op [3:0] $end
   $var wire 1 ) rst $end
   $var wire 1 * clk $end
   $var wire 8 # out [7:0] $end
   $var wire 1 $ carryout $end
   $var wire 1 % overflow $end
   $scope module dut $end
    $var wire 8 & in1 [7:0] $end
    $var wire 8 ' in2 [7:0] $end
    $var wire 4 ( op [3:0] $end
    $var wire 1 ) rst $end
    $var wire 1 * clk $end
    $var wire 8 # out [7:0] $end
    $var wire 1 $ carryout $end
    $var wire 1 % overflow $end
   $upscope $end
  $upscope $end
 $upscope $end
$enddefinitions $end


#0
b00000000 #
0$
0%
b00000000 &
b00000000 '
b0000 (
1)
0*
#5000
b00101011 #
b00011001 &
b00010010 '
0)
1*
#10000
0*
#15000
1*
#20000
0*
#25000
b00000111 #
b0001 (
1*
#30000
0*
#35000
b11000010 #
1%
b0010 (
1*
#40000
0*
#45000
b00000001 #
0%
b0011 (
1*
#50000
0*
#55000
b00010000 #
b0100 (
1*
#60000
0*
#65000
b00011011 #
b0101 (
1*
#70000
0*
#75000
b00001011 #
b0110 (
1*
#80000
0*
#85000
b11100110 #
b0111 (
1*
#90000
0*
#95000
b11001100 #
b1000 (
1*
#100000
0*
#105000
b01100110 #
b1001 (
1*
#110000
0*
#115000
b00110010 #
b1010 (
1*
#120000
0*
#125000
b10001100 #
b1011 (
1*
#130000
0*
#135000
b00000001 #
b1100 (
1*
#140000
0*
#145000
b00000000 #
b1101 (
1*
